polar_spark_df/__init__.py
polar_spark_df/benchmark.py
polar_spark_df/converter.py
polar_spark_df-0.1.0.dist-info/LICENSE
polar_spark_df-0.1.0.dist-info/METADATA
polar_spark_df-0.1.0.dist-info/WHEEL
polar_spark_df-0.1.0.dist-info/top_level.txt
polar_spark_df-0.1.0.dist-info/RECORD
